empymod/__init__.py
empymod/__main__.py
empymod/filters.py
empymod/io.py
empymod/kernel.py
empymod/model.py
empymod/transform.py
empymod/utils.py
empymod/version.py
empymod/scripts/__init__.py
empymod/scripts/fdesign.py
empymod/scripts/tmtemod.py
empymod_plain-2.2.1.post1.dist-info/LICENSE
empymod_plain-2.2.1.post1.dist-info/METADATA
empymod_plain-2.2.1.post1.dist-info/NOTICE
empymod_plain-2.2.1.post1.dist-info/WHEEL
empymod_plain-2.2.1.post1.dist-info/entry_points.txt
empymod_plain-2.2.1.post1.dist-info/top_level.txt
empymod_plain-2.2.1.post1.dist-info/RECORD
