Metadata-Version: 2.1
Name: empymod-plain
Version: 2.2.1.post1
Summary: Open-source full 3D electromagnetic modeller for 1D VTI media
Home-page: https://emsig.xyz
Author: The emsig community
Author-email: info@emsig.xyz
License: Apache-2.0
Classifier: Development Status :: 5 - Production/Stable
Classifier: License :: OSI Approved :: Apache Software License
Classifier: Programming Language :: Python :: 3.7
Classifier: Programming Language :: Python :: 3.8
Classifier: Programming Language :: Python :: 3.9
Classifier: Programming Language :: Python :: 3.10
Requires-Python: >=3.7
License-File: LICENSE
License-File: NOTICE
Requires-Dist: scipy (>=1.4)
